[
  {
    "id": "880cd355-91f9-4dcf-b767-11191b86a7ac",
    "name": "Dr. Hugo Bartoletti",
    "phone": "1-256-837-9767 x44696",
    "email": "Rosanna_Hagenes3@hotmail.com",
    "job": "District Applications Technician"
  },
  {
    "id": "a2858e1c-0281-42fd-a8ed-253cd51cda72",
    "name": "Terence Pouros",
    "phone": "518-512-8919 x9350",
    "email": "Quincy_Fritsch@yahoo.com",
    "job": "Chief Directives Assistant"
  },
  {
    "id": "b7e99c1b-97a5-415a-9e76-59b19eb5f987",
    "name": "Nicholas Sipes",
    "phone": "871.627.4891 x02301",
    "email": "Celia37@yahoo.com",
    "job": "Global Interactions Officer"
  },
  {
    "id": "60bbb5db-c166-4007-8389-286cd615fab3",
    "name": "Levi McCullough",
    "phone": "(759) 368-9907 x62278",
    "email": "Salvatore99@gmail.com",
    "job": "Corporate Creative Facilitator"
  },
  {
    "id": "97e48a10-c79e-4a65-86d3-e8291df7a0a2",
    "name": "Archie Schaefer",
    "phone": "(345) 498-7803 x689",
    "email": "Royal_Weissnat@hotmail.com",
    "job": "District Accounts Consultant"
  }
]